_login.py
gtrends.py
gtrends-0.2.2.dist-info/DESCRIPTION.rst
gtrends-0.2.2.dist-info/METADATA
gtrends-0.2.2.dist-info/RECORD
gtrends-0.2.2.dist-info/WHEEL
gtrends-0.2.2.dist-info/metadata.json
gtrends-0.2.2.dist-info/top_level.txt
