Metadata-Version: 2.0
Name: gtrends
Version: 0.2.2
Summary: Automated Google Trends downloader
Home-page: https://github.com/ecsalina/gtrends
Author: Eric Salina
Author-email: UNKNOWN
License: MIT
Keywords: Google,Trends,API,gtrends
Platform: UNKNOWN
Classifier: Development Status :: 5 - Production/Stable
Classifier: Intended Audience :: Developers
Classifier: Topic :: Utilities
Classifier: License :: OSI Approved :: MIT License
Classifier: Programming Language :: Python :: 2.7
Classifier: Programming Language :: Python :: 3.4
Classifier: Programming Language :: Python :: 3.5
Requires-Dist: six
